__init__.py
pycampbellcloud.py
pycampbellcloud-0.9.1.dist-info/licenses/LICENSE
pycampbellcloud-0.9.1.dist-info/METADATA
pycampbellcloud-0.9.1.dist-info/WHEEL
pycampbellcloud-0.9.1.dist-info/top_level.txt
pycampbellcloud-0.9.1.dist-info/RECORD
