Metadata-Version: 2.4
Name: pycampbellcloud
Version: 0.9.1
Summary: A package for interfacing with Campbell Cloud API.
Author-email: Nate Turner <nathan.turner@campbellsci.com>
License-Expression: Apache-2.0
Project-URL: Homepage, https://github.com/LlamaWhisp3r3r/pycampbellcloud
Project-URL: Documentation, https://us-west-2.campbell-cloud.com/api/v1/docs/
Requires-Python: >=3.12
License-File: LICENSE
Requires-Dist: requests
Dynamic: license-file
